{"title":"인터파크 티켓 모바일","url":"http://mticket.interpark.com/Notice/","favicon":"http://mticket.interpark.com/Notice/favicon.ico","elements":[{"title":"2024 라이브가족뮤지컬 〈산타클로스와브레멘음악대〉 -부산","contents":"2024.10.11\n                                    <span>09:00</span>","link":"http://mticket.interpark.com/Notice/NoticeView?bn=34&no=53003","retrieved":1728572972767,"image":"http://ticketimage.interpark.com/Play/image/large/24/24014750_p.gif"},{"title":"홍주의병이여, 말하라! - 광천문예회관","contents":"2024.10.11\n                                    <span>09:00</span>","link":"http://mticket.interpark.com/Notice/NoticeView?bn=34&no=53063","retrieved":1728606985868,"image":"http://ticketimage.interpark.com/Play/image/large/24/24014725_p.gif"},{"title":"홍주의병이여, 말하라! - 홍주문화회관","contents":"2024.10.11\n                                    <span>09:00</span>","link":"http://mticket.interpark.com/Notice/NoticeView?bn=34&no=53064","retrieved":1728616450644,"image":"http://ticketimage.interpark.com/Play/image/large/24/24014690_p.gif"},{"title":"가족뮤지컬 산타와 루돌프 - 성남","contents":"2024.10.11\n                                    <span>10:00</span>","link":"http://mticket.interpark.com/Notice/NoticeView?bn=34&no=53010","retrieved":1728572972771,"image":"http://ticketimage.interpark.com/Play/image/large/24/24014630_p.gif"},{"title":"[대구] 2024 조항조 연말 라이브 쇼!","contents":"2024.10.11\n                                    <span>11:00</span>","link":"http://mticket.interpark.com/Notice/NoticeView?bn=34&no=53011","retrieved":1728572972804,"image":"http://ticketimage.interpark.com/Play/image/large/24/24014687_p.gif"},{"title":"뮤지컬 〈조선 이야기꾼 전기수: 나잇-츠〉","contents":"2024.10.11\n                                    <span>11:00</span>","link":"http://mticket.interpark.com/Notice/NoticeView?bn=34&no=53034","retrieved":1728572972808,"image":"http://ticketimage.interpark.com/Play/image/large/24/24014746_p.gif"},{"title":"임태경 20주년 기념 전국 투어 콘서트 〈임태경.COM:Color of Music〉 in 대구","contents":"2024.10.11\n                                    <span>12:00</span>","link":"http://mticket.interpark.com/Notice/NoticeView?bn=34&no=53018","retrieved":1728572972810,"image":"http://ticketimage.interpark.com/Play/image/large/24/24014704_p.gif"},{"title":"시가렛 애프터 섹스 내한공연 (Cigarettes After Sex: X’s World Tour 2025)","contents":"2024.10.11\n                                    <span>12:00</span>","link":"http://mticket.interpark.com/Notice/NoticeView?bn=34&no=52993","retrieved":1728572972811,"image":"http://ticketimage.interpark.com/Play/image/large/24/24014570_p.gif"},{"title":"2024 연극〈신바람 삼대〉 :대학로 컴백!","contents":"2024.10.11\n                                    <span>14:00</span>","link":"http://mticket.interpark.com/Notice/NoticeView?bn=34&no=53019","retrieved":1728644604763,"image":"http://ticketimage.interpark.com/Play/image/large/24/24014723_p.gif"},{"title":"뮤지컬 〈빈센트 반 고흐〉","contents":"2024.10.11\n                                    <span>14:00</span>","link":"http://mticket.interpark.com/Notice/NoticeView?bn=34&no=52996","retrieved":1728572972814,"image":"http://ticketimage.interpark.com/Play/image/large/24/24013762_p.gif"}]}