{"title":"인터파크 티켓 모바일","url":"http://mticket.interpark.com/Notice/","favicon":"http://mticket.interpark.com/Notice/favicon.ico","elements":[{"title":"제1회 DJC 재즈 라이브 콘서트［New Wave］","contents":"2024.05.10\n                                    <span>00:00</span>","link":"http://mticket.interpark.com/Notice/NoticeView?bn=34&no=51251","retrieved":1715349754869,"image":"http://ticketimage.interpark.com/Play/image/large/24/24003218_p.gif"},{"title":"메드베디","contents":"2024.05.10\n                                    <span>09:00</span>","link":"http://mticket.interpark.com/Notice/NoticeView?bn=34&no=51272","retrieved":1715349754874,"image":"http://ticketimage.interpark.com/Play/image/large/24/24006472_p.gif"},{"title":"골든걸스 콘서트 - 대구","contents":"2024.05.10\n                                    <span>11:00</span>","link":"http://mticket.interpark.com/Notice/NoticeView?bn=34&no=51277","retrieved":1715349754874,"image":"http://ticketimage.interpark.com/Play/image/large/24/24006670_p.gif"},{"title":"그 놀 때 콘서트","contents":"2024.05.10\n                                    <span>12:00</span>","link":"http://mticket.interpark.com/Notice/NoticeView?bn=34&no=51276","retrieved":1715349754876,"image":"http://ticketimage.interpark.com/Play/image/large/24/24006626_p.gif"},{"title":"알렉상드르 캉토로프 피아노 리사이틀","contents":"2024.05.10\n                                    <span>13:00</span>","link":"http://mticket.interpark.com/Notice/NoticeView?bn=34&no=51291","retrieved":1715349754880,"image":"http://ticketimage.interpark.com/Play/image/large/24/24006591_p.gif"},{"title":"진성 30주년 기념 콘서트 〈진성 빅쇼〉 - 고양","contents":"2024.05.10\n                                    <span>14:00</span>","link":"http://mticket.interpark.com/Notice/NoticeView?bn=34&no=51290","retrieved":1715349754880,"image":"http://ticketimage.interpark.com/Play/image/large/24/24006751_p.gif"},{"title":"가족뮤지컬 〈꼬마버스 타요 - 용감한 구조대 레스큐 타요〉 - 고양","contents":"2024.05.10\n                                    <span>14:00</span>","link":"http://mticket.interpark.com/Notice/NoticeView?bn=34&no=51289","retrieved":1715349754882,"image":"http://ticketimage.interpark.com/Play/image/large/24/24006577_p.gif"},{"title":"뮤지컬 〈빨래〉 29차","contents":"2024.05.10\n                                    <span>14:00</span>","link":"http://mticket.interpark.com/Notice/NoticeView?bn=34&no=51285","retrieved":1715349754884,"image":"http://ticketimage.interpark.com/Play/image/large/24/24006709_p.gif"},{"title":"연극〈늘근도둑이야기〉","contents":"2024.05.10\n                                    <span>14:00</span>","link":"http://mticket.interpark.com/Notice/NoticeView?bn=34&no=51281","retrieved":1715349754885,"image":"http://ticketimage.interpark.com/Play/image/large/22/22001159_p.gif"},{"title":"[대전] 2024 뮤지컬 왕자대전","contents":"2024.05.10\n                                    <span>14:00</span>","link":"http://mticket.interpark.com/Notice/NoticeView?bn=34&no=51280","retrieved":1715349754887,"image":"http://ticketimage.interpark.com/Play/image/large/24/24006729_p.gif"}]}