{"title":"멜론 티켓","url":"https://ticket.melon.com/csoon/index.htm","favicon":"https://ticket.melon.com/csoon/favicon.ico","elements":[{"title":"생각의 여름 단독 콘서트 ‘마음이라는 마을’：롤링 29주년 기념 공연 티켓 오픈 안내","contents":"2024.05.27(월) 20:00","link":"https://ticket.melon.com/csoon/detail.htm?csoonId=8827","retrieved":1716217371017},{"title":"2024 NAM GYURI FAN CONCERT：Lux 티켓 오픈 안내","contents":"2024.05.22(수) 20:00","link":"https://ticket.melon.com/csoon/detail.htm?csoonId=8826","retrieved":1716217371033},{"title":"구남과여라이딩스텔라 전국투어－공주 티켓 오픈 안내","contents":"2024.05.21(화) 18:00","link":"https://ticket.melon.com/csoon/detail.htm?csoonId=8825","retrieved":1716217371036},{"title":"EVEN IF WE WANT TO BE HIGH 티켓 오픈 안내","contents":"2024.05.24(금) 20:00","link":"https://ticket.melon.com/csoon/detail.htm?csoonId=8823","retrieved":1716217371041},{"title":"Creepy Nuts ONE MAN TOUR 2024 티켓 오픈 안내","contents":"2024.05.20(월) 12:00","link":"https://ticket.melon.com/csoon/detail.htm?csoonId=8822","retrieved":1716217371042},{"title":"기억의 습작：어제，오늘 그리고 티켓 오픈 안내","contents":"2024.05.20(월) 18:00","link":"https://ticket.melon.com/csoon/detail.htm?csoonId=8821","retrieved":1716217371047},{"title":"홍성준 Fanmeeting 〈약속〉 추가 티켓 오픈 안내","contents":"2024.05.21(화) 20:00","link":"https://ticket.melon.com/csoon/detail.htm?csoonId=8820","retrieved":1716217371048},{"title":"2024 미술관 옆 공연장－그림에 음악과 향기를 더하다 티켓 오픈 안내","contents":"2024.05.20(월) 14:00","link":"https://ticket.melon.com/csoon/detail.htm?csoonId=8819","retrieved":1716217371052},{"title":"뮤지컬 〈헤드윅〉 6차 티켓 오픈 안내","contents":"2024.05.23(목) 14:00","link":"https://ticket.melon.com/csoon/detail.htm?csoonId=8818","retrieved":1716217371056},{"title":"모브닝 단독 콘서트 〈한숨의 모양〉 티켓 오픈 안내","contents":"2024.05.24(금) 20:00","link":"https://ticket.melon.com/csoon/detail.htm?csoonId=8817","retrieved":1716217371064}]}