{"title":"멜론 티켓","url":"https://ticket.melon.com/csoon/index.htm","favicon":"https://ticket.melon.com/csoon/favicon.ico","elements":[{"title":"뮤지컬 〈맥베스〉 티켓 오픈 안내","contents":"2024.10.22(화) 14:00","link":"https://ticket.melon.com/csoon/detail.htm?csoonId=9458","retrieved":1730930859395},{"title":"우리집 음악회 티켓 오픈 안내","contents":"2024.11.11(월) 20:00","link":"https://ticket.melon.com/csoon/detail.htm?csoonId=9566","retrieved":1730930859396},{"title":"Song Sohee 1st Concert：風流（풍류）티켓 오픈 안내","contents":"2024.11.13(수) 19:00","link":"https://ticket.melon.com/csoon/detail.htm?csoonId=9565","retrieved":1730930859397},{"title":"아야츠노 유니 1st solo concert “Christmas On The Merry Go Round\" 티켓 오픈 안내","contents":"오픈일정 보기 &gt;","link":"https://ticket.melon.com/csoon/detail.htm?csoonId=9564","retrieved":1730930859399},{"title":"에이퍼즈 앨범발매 쇼케이스 티켓 오픈 안내","contents":"2024.11.08(금) 11:00","link":"https://ticket.melon.com/csoon/detail.htm?csoonId=9563","retrieved":1730930859400},{"title":"2024 KAVE 단독 콘서트 투어 〈Say My Name〉 서울, 부산 티켓 오픈 안내","contents":"오픈일정 보기 &gt;","link":"https://ticket.melon.com/csoon/detail.htm?csoonId=9562","retrieved":1730930859404},{"title":"먼데이프로젝트 시즌7 [김바다밴드 단독 콘서트 ‘바다가 시작되는 곳’] 티켓 오픈 안내","contents":"2024.11.13(수) 20:00","link":"https://ticket.melon.com/csoon/detail.htm?csoonId=9561","retrieved":1730930859405},{"title":"2024 KOKYUNGPYO FANMETTING [KOKYUNGPYO SHOW] 티켓 오픈 안내","contents":"2024.11.13(수) 20:00","link":"https://ticket.melon.com/csoon/detail.htm?csoonId=9560","retrieved":1730930859406},{"title":"2024 B-day PARTY - CHANYEOL [OFF THE RECORD] 티켓 오픈 안내","contents":"오픈일정 보기 &gt;","link":"https://ticket.melon.com/csoon/detail.htm?csoonId=9559","retrieved":1730930859408},{"title":"NO HIPHOP NO LIFE (노힢노랖) Vol.003 - 언에듀케이티드 키드(UNEDUCATED KID) 티켓 오픈 안내","contents":"2024.11.07(목) 18:00","link":"https://ticket.melon.com/csoon/detail.htm?csoonId=9558","retrieved":1730930859409},{"title":"2024 케이시 콘서트 〈아홉번째 겨울: 사랑의 편린〉 티켓 오픈 안내","contents":"2024.11.08(금) 20:00","link":"https://ticket.melon.com/csoon/detail.htm?csoonId=9556","retrieved":1730930859410}]}