{"title":"멜론 티켓","url":"https://ticket.melon.com/csoon/index.htm","favicon":"https://ticket.melon.com/csoon/favicon.ico","elements":[{"title":"신촌 BLUES 콘서트 티켓 오픈 안내","contents":"2024.02.27(화) 16:00","link":"https://ticket.melon.com/csoon/detail.htm?csoonId=8461","retrieved":1708671711706},{"title":"HISTORY 안치환 콘서트 티켓 오픈 안내","contents":"2024.02.27(화) 16:00","link":"https://ticket.melon.com/csoon/detail.htm?csoonId=8460","retrieved":1708671711707},{"title":"권서경 팬콘서트 〈Fly High〉 티켓 오픈 안내","contents":"2024.02.27(화) 14:00","link":"https://ticket.melon.com/csoon/detail.htm?csoonId=8458","retrieved":1708671711707},{"title":"뮤지컬 〈그레이트 코멧〉 1차 티켓 오픈 안내","contents":"2024.02.28(수) 14:00","link":"https://ticket.melon.com/csoon/detail.htm?csoonId=8457","retrieved":1708671711707},{"title":"이병찬 소극장 콘서트［MY COSMOS］티켓 오픈 안내","contents":"2024.02.26(월) 20:00","link":"https://ticket.melon.com/csoon/detail.htm?csoonId=8455","retrieved":1708671711708},{"title":"싸이코드 감제이 빨간약 콘서트 티켓 오픈 안내","contents":"2024.02.26(월) 21:00","link":"https://ticket.melon.com/csoon/detail.htm?csoonId=8454","retrieved":1708671711710},{"title":"워터밤 서울 2024（WATERBOMB SEOUL 2024）티켓 오픈 안내","contents":"2024.02.23(금) 13:00","link":"https://ticket.melon.com/csoon/detail.htm?csoonId=8452","retrieved":1708671711712},{"title":"2024 IU H．E．R．WORLD TOUR CONCERT IN SEOUL 시야제한석 유애나 6기 대상 추가 티켓 오픈 안내","contents":"오픈일정 보기 &gt;","link":"https://ticket.melon.com/csoon/detail.htm?csoonId=8451","retrieved":1708671711725},{"title":"먼데이프로젝트 시즌7 ORIGINAL［피에타 단독 콘서트］티켓 오픈 안내","contents":"2024.02.29(목) 20:00","link":"https://ticket.melon.com/csoon/detail.htm?csoonId=8450","retrieved":1708671711726},{"title":"브라운티거 3집 정규［이립］콘서트 티켓 오픈 안내","contents":"2024.02.29(목) 18:00","link":"https://ticket.melon.com/csoon/detail.htm?csoonId=8449","retrieved":1708671711729}]}