{"title":"예스24 티켓","url":"http://ticket.yes24.com/New/Notice/NoticeMain.aspx","favicon":"http://tkfile.yes24.com/img/icon.png","elements":[{"title":"뮤지컬 〈매직 판타지아-도로시 리턴즈〉 2차 티켓오픈 안내","contents":"2023.06.21(수) 11:00","link":"http://ticket.yes24.com/New/Notice/NoticeMain.aspx#id=13182","retrieved":1686921040101},{"title":"단독판매","contents":"2023.06.19(월) 20:00","link":"http://ticket.yes24.com/New/Notice/NoticeMain.aspx#id=13181","retrieved":1686921040102},{"title":"뮤지컬 〈구텐버그〉 오픈위크 티켓오픈 안내","contents":"2023.06.22(목) 14:00","link":"http://ticket.yes24.com/New/Notice/NoticeMain.aspx#id=13180","retrieved":1686921040124},{"title":"쇼뮤지컬 〈드림하이〉 3차 티켓오픈 안내","contents":"2023.06.19(월) 14:00","link":"http://ticket.yes24.com/New/Notice/NoticeMain.aspx#id=13179","retrieved":1686921040125},{"title":"10-FEET ＂COLLINS＂ TOUR 2023 in Korea 추가 티켓 오픈 안내","contents":"2023.06.19(월) 18:00","link":"http://ticket.yes24.com/New/Notice/NoticeMain.aspx#id=13178","retrieved":1686921040125},{"title":"단독판매","contents":"2023.06.27(화) 20:00<a class=\"noti-btn-pop\" presaletit1=\"팬클럽 선예매\" presaletit2=\"\" presaletime1=\"2023.06.26(월) 20:00\" presaletime2=\"\"><img src=\"http://tkfile.yes24.com/imgNew/common/btn-notice1.png\" alt=\"\"></a>","link":"http://ticket.yes24.com/New/Notice/NoticeMain.aspx#id=13177","retrieved":1686921040150},{"title":"단독판매","contents":"2023.06.23(금) 20:00<a class=\"noti-btn-pop\" presaletit1=\"팬클럽 선예매\" presaletit2=\"\" presaletime1=\"2023.06.22(목) 20:00\" presaletime2=\"\"><img src=\"http://tkfile.yes24.com/imgNew/common/btn-notice1.png\" alt=\"\"></a>","link":"http://ticket.yes24.com/New/Notice/NoticeMain.aspx#id=13176","retrieved":1686921040153},{"title":"단독판매","contents":"2023.06.23(금) 18:00","link":"http://ticket.yes24.com/New/Notice/NoticeMain.aspx#id=13175","retrieved":1686921040162},{"title":"2023 부산국제주류산업박람회 티켓오픈 안내","contents":"2023.06.19(월) 14:00","link":"http://ticket.yes24.com/New/Notice/NoticeMain.aspx#id=13174","retrieved":1686921040171},{"title":"Woodstock Music ＆ Art Fair 2023 티켓 오픈 안내","contents":"2023.06.15(목) 17:00","link":"http://ticket.yes24.com/New/Notice/NoticeMain.aspx#id=13173","retrieved":1686921040179},{"title":"Soundberry Festa’ 23 티켓 오픈 안내","contents":"2023.06.16(금) 18:00","link":"http://ticket.yes24.com/New/Notice/NoticeMain.aspx#id=13172","retrieved":1686921040183},{"title":"JUMF 2023 전주얼티밋뮤직페스티벌 얼리버드 티켓 오픈 안내","contents":"2023.06.19(월) 12:00","link":"http://ticket.yes24.com/New/Notice/NoticeMain.aspx#id=13171","retrieved":1686921040183},{"title":"부천아트센터 <조수미 & 베를린필 12 첼리스트> / <조성진 피아노 리사이틀> 합창석 추가 오픈 ..","contents":"2023.06.20(화) 14:00","link":"http://ticket.yes24.com/New/Notice/NoticeMain.aspx#id=13170","retrieved":1686921040185},{"title":"뮤지컬 〈수레바퀴 아래서〉 2차 티켓오픈 안내","contents":"2023.06.21(수) 14:00","link":"http://ticket.yes24.com/New/Notice/NoticeMain.aspx#id=13169","retrieved":1686921040189},{"title":"연극 <라스트 세션(Freud’s Last Session)> 1차 티켓오픈 안내","contents":"2023.06.21(수) 11:00","link":"http://ticket.yes24.com/New/Notice/NoticeMain.aspx#id=13168","retrieved":1686921040190},{"title":"단독판매","contents":"2023.06.22(목) 10:00","link":"http://ticket.yes24.com/New/Notice/NoticeMain.aspx#id=13167","retrieved":1686921040194},{"title":"단독판매","contents":"2023.06.22(목) 10:00","link":"http://ticket.yes24.com/New/Notice/NoticeMain.aspx#id=13166","retrieved":1686921040199},{"title":"단독판매","contents":"2023.06.22(목) 10:00","link":"http://ticket.yes24.com/New/Notice/NoticeMain.aspx#id=13165","retrieved":1686921040206},{"title":"단독판매","contents":"2023.06.22(목) 10:00","link":"http://ticket.yes24.com/New/Notice/NoticeMain.aspx#id=13164","retrieved":1686921040213},{"title":"단독판매","contents":"2023.06.22(목) 10:00","link":"http://ticket.yes24.com/New/Notice/NoticeMain.aspx#id=13163","retrieved":1686921040213}]}